alimiji_film_sdk/__init__.py
alimiji_film_sdk/film_client.py
alimiji_film_sdk/film_config.py
alimiji_film_sdk/schemas/__init__.py
alimiji_film_sdk/schemas/schemas.py
alimiji_film_sdk-0.0.5.dist-info/METADATA
alimiji_film_sdk-0.0.5.dist-info/WHEEL
alimiji_film_sdk-0.0.5.dist-info/top_level.txt
alimiji_film_sdk-0.0.5.dist-info/RECORD
