Metadata-Version: 2.4
Name: alimiji_film_sdk
Version: 0.0.5
Summary: SDK Python pour accéder à l’API MovieLens (Data Analysts/Data Scientists friendly)
Author: [Ali MIJIYAWA]
Classifier: Development Status :: 3 - Alpha
Classifier: Programming Language :: Python :: 3
Classifier: License :: OSI Approved :: MIT License
Classifier: Operating System :: OS Independent
Requires-Python: >=3.10
Requires-Dist: httpx>=0.28.1
Requires-Dist: backoff>=2.2.1
Requires-Dist: pydantic>=2.11.7
Requires-Dist: pandas>=2.2.3
Requires-Dist: numpy>=2.2.4
Requires-Dist: python-dotenv>=1.1.1
